prove_assignment/__init__.py
prove_assignment/main.py
prove_assignment-0.0.1.dist-info/License.txt
prove_assignment-0.0.1.dist-info/METADATA
prove_assignment-0.0.1.dist-info/WHEEL
prove_assignment-0.0.1.dist-info/top_level.txt
prove_assignment-0.0.1.dist-info/RECORD
