Metadata-Version: 2.1
Name: prove-assignment
Version: 0.0.1
Summary: UNKNOWN
Home-page: UNKNOWN
Author: Akshay Pawar
Author-email: author@example.com
License: MIT
Platform: UNKNOWN
Classifier: Programming Language :: Python :: 3
Classifier: License :: OSI Approved :: MIT License
Classifier: Operating System :: OS Independent
